kalkulator_ngaco/__init__.py
kalkulator_ngaco/__main__.py
kalkulator_ngaco/config.py
kalkulator_ngaco/core.py
kalkulator_ngaco-0.1.1.dist-info/METADATA
kalkulator_ngaco-0.1.1.dist-info/WHEEL
kalkulator_ngaco-0.1.1.dist-info/entry_points.txt
kalkulator_ngaco-0.1.1.dist-info/top_level.txt
kalkulator_ngaco-0.1.1.dist-info/RECORD
