Metadata-Version: 2.4
Name: kalkulator-ngaco
Version: 0.1.1
Summary: Kalkulator ngawur tapi lucu. Jangan percaya hasilnya.
Author-email: Nama Kamu <email@example.com>
Requires-Python: >=3.7
